fetch/__init__.py
fetch/bin.py
fetch/box.py
fetch/drawer.py
fetch/fetch_env.py
fetch/gym_fetch.py
fetch/no_lid.py
fetch/scratch_fetch_debug_obs.py
fetch/stack_two.py
fetch/wrappers.py
fetch/assets/LICENSE.md
fetch/assets/bin.xml
fetch/assets/bin_null.xml
fetch/assets/box.xml
fetch/assets/box_bin.xml
fetch/assets/box_bin_drawer.xml
fetch/assets/box_block.xml
fetch/assets/box_no_lid.xml
fetch/assets/clean_table.xml
fetch/assets/drawer.xml
fetch/assets/drawer_bin.xml
fetch/assets/drawer_block.xml
fetch/assets/pick_place.xml
fetch/assets/push.xml
fetch/assets/reach.xml
fetch/assets/robot.xml
fetch/assets/shared.xml
fetch/assets/slide.xml
fetch/assets/stack_two.xml
fetch/assets/twin_box.xml
fetch/assets/objects/bin.xml
fetch/assets/objects/bin_tall.xml
fetch/assets/objects/bin_tall_purple.xml
fetch/assets/objects/cabinet.xml
fetch/assets/objects/drawer.xml
fetch/assets/objects/lid.xml
fetch/assets/stls/base_link_collision.stl
fetch/assets/stls/bellows_link_collision.stl
fetch/assets/stls/elbow_flex_link_collision.stl
fetch/assets/stls/estop_link.stl
fetch/assets/stls/forearm_roll_link_collision.stl
fetch/assets/stls/gripper_link.stl
fetch/assets/stls/head_pan_link_collision.stl
fetch/assets/stls/head_tilt_link_collision.stl
fetch/assets/stls/l_wheel_link_collision.stl
fetch/assets/stls/laser_link.stl
fetch/assets/stls/r_wheel_link_collision.stl
fetch/assets/stls/shoulder_lift_link_collision.stl
fetch/assets/stls/shoulder_pan_link_collision.stl
fetch/assets/stls/torso_fixed_link.stl
fetch/assets/stls/torso_lift_link_collision.stl
fetch/assets/stls/upperarm_roll_link_collision.stl
fetch/assets/stls/wrist_flex_link_collision.stl
fetch/assets/stls/wrist_roll_link_collision.stl
fetch/assets/textures/block.png
fetch/assets/textures/block_hidden.png
fetch/common/__init__.py
fetch/common/robot_env.py
fetch/common/rotations.py
fetch/common/utils.py
fetch/mixed_envs/__init__.py
fetch/mixed_envs/box_bin.py
fetch/mixed_envs/box_bin_drawer.py
fetch/mixed_envs/box_block.py
gym_fetch-0.2.2.dist-info/LICENSE
gym_fetch-0.2.2.dist-info/METADATA
gym_fetch-0.2.2.dist-info/WHEEL
gym_fetch-0.2.2.dist-info/top_level.txt
gym_fetch-0.2.2.dist-info/RECORD
