Metadata-Version: 2.1
Name: gym-fetch
Version: 0.2.2
Summary: A goal-conditioned multitask suite for the fetch robot
Home-page: https://github.com/geyang/gym-fetch
Author: Ge Yang<ge.ike.yang@gmail.com>
Author-email: ge.ike.yang@gmail.com
License: UNKNOWN
Platform: UNKNOWN
Requires-Dist: cmx
Requires-Dist: numpy
